csvsample/__init__.py
csvsample/csvsample.py
csvsample-0.1.4.dist-info/LICENSE.txt
csvsample-0.1.4.dist-info/METADATA
csvsample-0.1.4.dist-info/RECORD
csvsample-0.1.4.dist-info/WHEEL
csvsample-0.1.4.dist-info/entry_points.txt
csvsample-0.1.4.dist-info/top_level.txt
