Metadata-Version: 2.1
Name: csvsample
Version: 0.1.4
Summary: Create random samples from CSV file
Home-page: https://github.com/akngs/csvsample
Author: Alan Kang
Author-email: jania902@gmail.com
License: UNKNOWN
Platform: UNKNOWN
Classifier: Development Status :: 3 - Alpha
Classifier: Environment :: Console
Classifier: Intended Audience :: Developers
Classifier: Intended Audience :: Information Technology
Classifier: Intended Audience :: Science/Research
Classifier: License :: OSI Approved :: MIT License
Classifier: Topic :: Text Editors :: Text Processing
Classifier: Programming Language :: Python :: 3
Classifier: Programming Language :: Python :: 3.6
Requires-Dist: fire
Requires-Dist: xxhash
Provides-Extra: dev
Requires-Dist: check-manifest; extra == 'dev'
Provides-Extra: test
Requires-Dist: pytest; extra == 'test'
